{
  "brand": {
    "labelMain": "Krew",
    "labelAccent": "Razem",
    "link": "/"
  },
  "common": [
    {
      "label": "Punkty krwiodawstwa",
      "to": "/punkty-krwiodawstwa"
    }
  ],
  "roles": {
    "guest": [
      {
        "label": "Krwiodawca",
        "to": "/krwiodawca"
      },
      {
        "label": "Dla dawcy",
        "to": "/dla-dawcy"
      }
    ],
    "donor": [
      {
        "label": "Umów wizytę",
        "to": "/rezerwacja"
      },
      {
        "label": "Mój profil",
        "to": "/profil"
      }
    ],
    "admin": [
      {
        "label": "Panel",
        "to": "/admin"
      },
      {
        "label": "Zarządzaj wizytami",
        "to": "/admin/wizyty"
      }
    ]
  },
  "actions": {
    "guest": {
      "type": "link",
      "label": "Zaloguj się",
      "to": "/login-info"
    },
    "auth": [ 
      {
        "type": "button",
        "label": "Wyloguj",
        "action": "logout"
      }
    ]
  },
  "featureFlags": {
    "showBooking": true
  },
  "visibilityRules": [
    {
      "ifFlag": "showBooking",
      "show": [
        "/rezerwacja"
      ]
    }
  ]
}